custom/__init__.py
custom/admin.py
custom/apps.py
custom/models.py
custom/tests.py
custom/views.py
custom/migrations/0001_initial.py
custom/migrations/0002_auto_20210804_0828.py
custom/migrations/0003_alter_library_options.py
custom/migrations/__init__.py
demo/migrations/0001_initial.py
demo/migrations/0002_auto_20190619_1122.py
demo/migrations/0003_auto_20210325_2151.py
demo/migrations/__init__.py
view_breadcrumbs/__init__.py
view_breadcrumbs/apps.py
view_breadcrumbs/constants.py
view_breadcrumbs/utils.py
view_breadcrumbs/generic/__init__.py
view_breadcrumbs/generic/base.py
view_breadcrumbs/generic/create.py
view_breadcrumbs/generic/delete.py
view_breadcrumbs/generic/detail.py
view_breadcrumbs/generic/list.py
view_breadcrumbs/generic/update.py
view_breadcrumbs/locale/en_US/LC_MESSAGES/django.po
view_breadcrumbs/locale/fr/LC_MESSAGES/django.po
view_breadcrumbs/templates/view_breadcrumbs/bootstrap2.html
view_breadcrumbs/templates/view_breadcrumbs/bootstrap3.html
view_breadcrumbs/templates/view_breadcrumbs/bootstrap4.html
view_breadcrumbs/templates/view_breadcrumbs/bootstrap5.html
view_breadcrumbs/templatetags/__init__.py
view_breadcrumbs/templatetags/view_breadcrumbs.py
view_breadcrumbs/tests/__init__.py
view_breadcrumbs/tests/unit/__init__.py
view_breadcrumbs/tests/unit/test_breadcrumbs.py
django_view_breadcrumbs-2.5.1.dist-info/LICENSE
django_view_breadcrumbs-2.5.1.dist-info/METADATA
django_view_breadcrumbs-2.5.1.dist-info/WHEEL
django_view_breadcrumbs-2.5.1.dist-info/top_level.txt
django_view_breadcrumbs-2.5.1.dist-info/RECORD
