Metadata-Version: 2.1
Name: django-view-breadcrumbs
Version: 2.5.1
Summary: Django generic view breadcrumbs
Home-page: https://github.com/tj-django/django-view-breadcrumbs
Author: Tonye Jack
Author-email: jtonye@ymail.com
Keywords: django breadcrumbs,breadcrumbs,django generic views breadcrumb
Classifier: Development Status :: 5 - Production/Stable
Classifier: Intended Audience :: Developers
Classifier: Topic :: Internet :: WWW/HTTP
Classifier: License :: OSI Approved :: BSD License
Classifier: Operating System :: OS Independent
Classifier: Programming Language :: Python :: 3.6
Classifier: Programming Language :: Python :: 3.7
Classifier: Programming Language :: Python :: 3.8
Classifier: Programming Language :: Python :: 3.9
Classifier: Programming Language :: Python :: 3.10
Classifier: Framework :: Django :: 1.11
Classifier: Framework :: Django :: 2.0
Classifier: Framework :: Django :: 2.1
Classifier: Framework :: Django :: 2.2
Classifier: Framework :: Django :: 3.0
Classifier: Framework :: Django :: 3.1
Classifier: Framework :: Django :: 3.2
Classifier: Framework :: Django :: 4.0
Classifier: Framework :: Django :: 4.1
Classifier: Framework :: Django :: 4.2
Requires-Python: >=3.6
Provides-Extra: development
Provides-Extra: docs
Provides-Extra: test
Provides-Extra: deploy
License-File: LICENSE
